kotobuki/__init__.py
kotobuki/mapping_updater/cli.py
kotobuki/mapping_updater/db.py
kotobuki/mapping_updater/io.py
kotobuki/mapping_updater/log.py
kotobuki/mapping_updater/relationship.py
kotobuki/mapping_updater/update_usagi.py
kotobuki-0.2.0.dist-info/METADATA
kotobuki-0.2.0.dist-info/WHEEL
kotobuki-0.2.0.dist-info/entry_points.txt
kotobuki-0.2.0.dist-info/licenses/LICENSE
kotobuki-0.2.0.dist-info/RECORD
