Metadata-Version: 2.4
Name: kotobuki
Version: 0.2.0
Summary: Usagi mappings update tool
Project-URL: Repository, https://github.com/thehyve/kotobuki
Project-URL: Documentation, https://github.com/thehyve/kotobuki/blob/main/docs/kotobuki.md
Project-URL: Bug Tracker, https://github.com/thehyve/kotobuki/issues
Project-URL: Changelog, https://github.com/thehyve/kotobuki/blob/main/CHANGELOG.md
License: Apache Software License
License-File: LICENSE
Classifier: Development Status :: 4 - Beta
Classifier: Intended Audience :: Developers
Classifier: License :: OSI Approved :: Apache Software License
Classifier: Natural Language :: English
Classifier: Operating System :: OS Independent
Classifier: Programming Language :: Python :: 3
Classifier: Programming Language :: Python :: 3.11
Classifier: Programming Language :: Python :: 3.12
Classifier: Programming Language :: Python :: 3.13
Classifier: Programming Language :: Python :: 3.14
Classifier: Programming Language :: Python :: Implementation :: CPython
Requires-Python: >=3.11
Requires-Dist: click>=8.2.1
Requires-Dist: omop-cdm>=0.4.0
Requires-Dist: pandas>=2.2.3
Requires-Dist: sqlalchemy>=2.0.41
